<properties>


  <data name="crop" value="false" parameterdata="postimage" id="pi1447790183613"/>  
  <data name="background" value="white" parameterdata="postimage" id="pi1447789384658"/>  
  <data name="layers" value="flatten" parameterdata="postimage" id="pi1447790062578"/>  
  <data name="prefwidth" value="1200" parameterdata="postimage" id="pi1447790100132"/>  
  <data name="prefheight" value="800" parameterdata="postimage" id="pi1447790093028"/>  
  <!--   data name="emautoheight" value="70%" parameterdata="imagepreview" id="pi14477904051024auto"/ -->
  <data name="useoriginalasinput" value="true" parameterdata="postimage" id="pi144779040orig"/>
  
  
  <data name="crop" value="false" parameterdata="blogimage" id="bpi1447789384dontcrop"/>  
  <data name="background" value="white" parameterdata="blogimage" id="bpi1447789384658share"/>  
  <data name="layers" value="flatten" parameterdata="blogimage" id="bpi1447790062578share"/>  
  <data name="prefwidth" value="600" parameterdata="blogimage" id="bpi1447790100132share"/>  
  <data name="prefheight" value="400" parameterdata="blogimage" id="bpi1447790093028share"/>  
  <data name="useoriginalasinput" value="true" parameterdata="blogimage" id="bpi144779040origshare"/>



  <data name="crop" value="true" parameterdata="shareimage" id="pi1447790183613share"/>  
  <data name="background" value="white" parameterdata="shareimage" id="pi1447789384658share"/>  
  <data name="layers" value="flatten" parameterdata="shareimage" id="pi1447790062578share"/>  
  <data name="gravity" value="Center" parameterdata="shareimage" id="pi1447790070354share"/>  
  <data name="prefwidth" value="1200" parameterdata="shareimage" id="pi1447790100132share"/>  
  <data name="prefheight" value="630" parameterdata="shareimage" id="pi1447790093028share"/>  
  <data name="x1" value="0" parameterdata="shareimage" id="pi1447790399176share"/>  
  <data name="y1" value="0" parameterdata="shareimage" id="pi1447790405247share"/>
  <data name="emautoheight" value="50%" parameterdata="shareimage" id="pi1447790405autoshare"/>
  <!--   data name="emautoheight" value="70%" parameterdata="imagepreview" id="pi14477904051024auto"/ -->
  <data name="useoriginalasinput" value="true" parameterdata="shareimage" id="pi144779040origshare"/>

  
</properties>